{
  "plugins": {
    "LuaSnip": {
      "rev": "642b0c595e11608b4c18219e93b88d7637af27bc",
      "src": "https://github.com/L3MON4D3/LuaSnip",
      "version": "2.0.0 - 3.0.0"
    },
    "blink.cmp": {
      "rev": "78336bc89ee5365633bcf754d93df01678b5c08f",
      "src": "https://github.com/saghen/blink.cmp",
      "version": "1.0.0 - 2.0.0"
    },
    "conform.nvim": {
      "rev": "619363c30309d29ffa631e67c8183f2a72caa373",
      "src": "https://github.com/stevearc/conform.nvim"
    },
    "copilot-lsp": {
      "rev": "1b6d8273594643f51bb4c0c1d819bdb21b42159d",
      "src": "https://github.com/copilotlsp-nvim/copilot-lsp"
    },
    "copilot.vim": {
      "rev": "a12fd5672110c8aa7e3c8419e28c96943ca179be",
      "src": "https://github.com/github/copilot.vim"
    },
    "dbtpal": {
      "rev": "981eab51609362712c64e3cf3fb773fe11f859b9",
      "src": "https://github.com/PedramNavid/dbtpal"
    },
    "diffview.nvim": {
      "rev": "4516612fe98ff56ae0415a259ff6361a89419b0a",
      "src": "https://github.com/sindrets/diffview.nvim"
    },
    "fidget.nvim": {
      "rev": "6f793b2bcd2d35e201c09520f698bb763220908a",
      "src": "https://github.com/j-hui/fidget.nvim"
    },
    "friendly-snippets": {
      "rev": "6cd7280adead7f586db6fccbd15d2cac7e2188b9",
      "src": "https://github.com/rafamadriz/friendly-snippets"
    },
    "github-nvim-theme": {
      "rev": "c106c9472154d6b2c74b74565616b877ae8ed31d",
      "src": "https://github.com/projekt0n/github-nvim-theme"
    },
    "gitsigns.nvim": {
      "rev": "eb60cc7b94c46005237fd34170d76f3a089a90aa",
      "src": "https://github.com/lewis6991/gitsigns.nvim"
    },
    "gruvbox-material": {
      "rev": "11d779b26a9ab2b3db8c22c6ac9fb6e8ed4fea79",
      "src": "https://github.com/sainnhe/gruvbox-material"
    },
    "gruvbox.nvim": {
      "rev": "154eb5ff5b96d0641307113fa385eaf0d36d9796",
      "src": "https://github.com/ellisonleao/gruvbox.nvim"
    },
    "guess-indent.nvim": {
      "rev": "84a4987ff36798c2fc1169cbaff67960aed9776f",
      "src": "https://github.com/NMAC427/guess-indent.nvim"
    },
    "kanagawa.nvim": {
      "rev": "bb85e4bfc8d89b0e62c8fa53ccdd13d12e2f77b3",
      "src": "https://github.com/rebelot/kanagawa.nvim"
    },
    "lazydev.nvim": {
      "rev": "ff2cbcba459b637ec3fd165a2be59b7bbaeedf0d",
      "src": "https://github.com/folke/lazydev.nvim"
    },
    "mason-lspconfig.nvim": {
      "rev": "47059d71b42d74b0a1e9f61c1d99d301039c3b5b",
      "src": "https://github.com/mason-org/mason-lspconfig.nvim"
    },
    "mason-tool-installer.nvim": {
      "rev": "443f1ef8b5e6bf47045cb2217b6f748a223cf7dc",
      "src": "https://github.com/WhoIsSethDaniel/mason-tool-installer.nvim"
    },
    "mason.nvim": {
      "rev": "2a6940af80375532e5e9e7c1f2fc6319a1b7a69d",
      "src": "https://github.com/mason-org/mason.nvim"
    },
    "mini.nvim": {
      "rev": "dc8a9918c3b1bc18a5fcd04d39b6d658074c0886",
      "src": "https://github.com/nvim-mini/mini.nvim"
    },
    "neoscroll.nvim": {
      "rev": "c8d29979cb0cb3a2437a8e0ae683fd82f340d3b8",
      "src": "https://github.com/karb94/neoscroll.nvim"
    },
    "noice.nvim": {
      "rev": "7bfd942445fb63089b59f97ca487d605e715f155",
      "src": "https://github.com/folke/noice.nvim"
    },
    "nui.nvim": {
      "rev": "de740991c12411b663994b2860f1a4fd0937c130",
      "src": "https://github.com/MunifTanjim/nui.nvim"
    },
    "nvim-autopairs": {
      "rev": "7b9923abad60b903ece7c52940e1321d39eccc79",
      "src": "https://github.com/windwp/nvim-autopairs"
    },
    "nvim-lspconfig": {
      "rev": "dd1c9b802c943278179a5d819369cda085b79d45",
      "src": "https://github.com/neovim/nvim-lspconfig"
    },
    "nvim-treesitter": {
      "rev": "4916d6592ede8c07973490d9322f187e07dfefac",
      "src": "https://github.com/nvim-treesitter/nvim-treesitter",
      "version": "'main'"
    },
    "oil-git-status.nvim": {
      "rev": "a3e2ccb00cb8822115e28a9a1791eda051d940c9",
      "src": "https://github.com/refractalize/oil-git-status.nvim"
    },
    "oil.nvim": {
      "rev": "b73018b75affd13fa38e2fc94ef753b465f770d7",
      "src": "https://github.com/stevearc/oil.nvim"
    },
    "plenary.nvim": {
      "rev": "74b06c6c75e4eeb3108ec01852001636d85a932b",
      "src": "https://github.com/nvim-lua/plenary.nvim"
    },
    "pretty_hover": {
      "rev": "934df974ef6158b100fe910e8556e6c4a66614c2",
      "src": "https://github.com/Fildo7525/pretty_hover"
    },
    "rose-pine": {
      "rev": "ff483051a47e27d84bdef47703538df1ed9f4a47",
      "src": "https://github.com/rose-pine/neovim"
    },
    "snacks.nvim": {
      "rev": "882c996cf28183f4d63640de0b4c02ec886d01f2",
      "src": "https://github.com/folke/snacks.nvim"
    },
    "telescope-ui-select.nvim": {
      "rev": "6e51d7da30bd139a6950adf2a47fda6df9fa06d2",
      "src": "https://github.com/nvim-telescope/telescope-ui-select.nvim"
    },
    "telescope.nvim": {
      "rev": "427b576c16792edad01a92b89721d923c19ad60f",
      "src": "https://github.com/nvim-telescope/telescope.nvim"
    },
    "todo-comments.nvim": {
      "rev": "31e3c38ce9b29781e4422fc0322eb0a21f4e8668",
      "src": "https://github.com/folke/todo-comments.nvim"
    },
    "tokyonight.nvim": {
      "rev": "cdc07ac78467a233fd62c493de29a17e0cf2b2b6",
      "src": "https://github.com/folke/tokyonight.nvim"
    },
    "which-key.nvim": {
      "rev": "3aab2147e74890957785941f0c1ad87d0a44c15a",
      "src": "https://github.com/folke/which-key.nvim"
    }
  }
}
